sigproextractor/__init__.py
sigproextractor/decomposition.py
sigproextractor/nmf_gpu.py
sigproextractor/sigpro.py
sigproextractor/single_sample.py
sigproextractor/subroutines.py
sigproextractor/version.py
sigproextractor/data/.DS_Store
sigproextractor/data/21_breast_WGS_substitutions.mat
sigproextractor/data/DBS_signatures_genome_builds.xlsx
sigproextractor/data/SBS_signatures_genome_builds.xlsx
sigproextractor/data/Samples.txt
sigproextractor/data/csvexample.csv
sigproextractor/data/sigProfiler_DBS_signatures.csv
sigproextractor/data/sigProfiler_ID_signatures.csv
sigproextractor/data/sigProfiler_SBS_signatures_2018_03_28.csv
sigproextractor/data/vcftest/.DS_Store
sigproextractor/data/vcftest/PD3851a.vcf
sigproextractor/data/vcftest/PD3890a.vcf
sigproextractor/data/vcftest/PD3904a.vcf
sigproextractor/data/vcftest/PD3905a.vcf
sigproextractor/data/vcftest/PD3945a.vcf
sigproextractor/data/vcftest/PD4005a.vcf
sigproextractor/data/vcftest/PD4006a.vcf
sigproextractor/data/vcftest/PD4085a.vcf
sigproextractor/data/vcftest/PD4086a.vcf
sigproextractor/data/vcftest/PD4088a.vcf
sigproextractor/data/vcftest/PD4103a.vcf
sigproextractor/data/vcftest/PD4107a.vcf
sigproextractor/data/vcftest/PD4109a.vcf
sigproextractor/data/vcftest/PD4115a.vcf
sigproextractor/data/vcftest/PD4116a.vcf
sigproextractor/data/vcftest/PD4120a.vcf
sigproextractor/data/vcftest/PD4192a.vcf
sigproextractor/data/vcftest/PD4194a.vcf
sigproextractor/data/vcftest/PD4198a.vcf
sigproextractor/data/vcftest/PD4199a.vcf
sigproextractor/data/vcftest/PD4248a.vcf
sigproextractor/data/vcftest/breast_genomes_all_indels.txt
sigproextractor/data/vcftest/breast_genomes_all_subs_simple_2.txt
sigproextractor-0.0.5.77.dist-info/LICENSE.txt
sigproextractor-0.0.5.77.dist-info/METADATA
sigproextractor-0.0.5.77.dist-info/WHEEL
sigproextractor-0.0.5.77.dist-info/top_level.txt
sigproextractor-0.0.5.77.dist-info/RECORD
