Metadata-Version: 2.1
Name: sigproextractor
Version: 0.0.5.77
Summary: Extracts mutational signatures from mutational catalogues
Home-page: https://github.com/AlexandrovLab/SigProfilerExtractor.git
Author: S Mishu Ashiqul Islam
Author-email: m0islam@ucsd.edu
License: UCSD
Platform: UNKNOWN
Requires-Dist: matplotlib (>=2.2.2)
Requires-Dist: scipy (>=1.3.0)
Requires-Dist: torch (>=1.1.0)
Requires-Dist: numpy (>=1.14.4)
Requires-Dist: pandas (>=0.23.4)
Requires-Dist: nimfa (>=1.1.0)
Requires-Dist: SigProfilerMatrixGenerator (>=1.0.17)
Requires-Dist: sigProfilerPlotting (>=1.0.5)
Requires-Dist: pillow
Requires-Dist: statsmodels (>=0.9.0)
Requires-Dist: scikit-learn (>=0.20.2)
Requires-Dist: psutil (>=5.6.1)
Requires-Dist: xlrd (>=1.0.0)
